tarina/__init__.py
tarina/_lru_c.pyi
tarina/_lru_py.py
tarina/_op.h
tarina/_string_c.pxd
tarina/_string_c.pyi
tarina/_string_c.pyx
tarina/_string_py.py
tarina/const.py
tarina/context.py
tarina/date.py
tarina/dcls.py
tarina/generic.py
tarina/guard.py
tarina/lru.py
tarina/lru.pyi
tarina/py.typed
tarina/signature.py
tarina/string.py
tarina/tools.py
tarina/trie.py
tarina/i18n/.config.json
tarina/i18n/.lang.schema.json
tarina/i18n/.template.json
tarina/i18n/.template.schema.json
tarina/i18n/en-US.json
tarina/i18n/model.py
tarina/i18n/zh-CN.json
tarina/lang/__init__.py
tarina/lang/__main__.py
tarina/lang/model.py
tarina/lang/schema.py
tarina-0.7.3.dist-info/licenses/LICENSE
tarina-0.7.3.dist-info/METADATA
tarina-0.7.3.dist-info/WHEEL
tarina-0.7.3.dist-info/entry_points.txt
tarina-0.7.3.dist-info/top_level.txt
tarina-0.7.3.dist-info/RECORD
