Metadata-Version: 2.4
Name: tarina
Version: 0.7.3
Summary: A collection of common utils for Arclet
Author-email: RF-Tar-Railt <rf_tar_railt@qq.com>
License: MIT
Requires-Python: >=3.9
License-File: LICENSE
Requires-Dist: typing-extensions>=4.4.0
Provides-Extra: yaml
Requires-Dist: pyyaml>=6.0.1; extra == "yaml"
Dynamic: license-file
